{"nodes": [{"id": "tailwind_css", "label": "Tailwind CSS", "file_type": "concept", "source_file": "Phase 1/POC/Geminipro2.5/test-doneproject-tailwind/MCSS-missing-vs-tailwind.md", "source_location": null, "source_url": null, "captured_at": null, "author": null, "contributor": null}, {"id": "mcss_vs_tailwind_comparison", "label": "MCSS vs Tailwind comparison report", "file_type": "document", "source_file": "Phase 1/POC/Geminipro2.5/test-doneproject-tailwind/MCSS-missing-vs-tailwind.md", "source_location": null, "source_url": null, "captured_at": null, "author": null, "contributor": null}], "edges": [{"source": "mcss_vs_tailwind_comparison", "target": "mcss_framework", "relation": "references", "confidence": "EXTRACTED", "confidence_score": 1.0, "source_file": "Phase 1/POC/Geminipro2.5/test-doneproject-tailwind/MCSS-missing-vs-tailwind.md", "source_location": null, "weight": 1.0}, {"source": "mcss_vs_tailwind_comparison", "target": "tailwind_css", "relation": "references", "confidence": "EXTRACTED", "confidence_score": 1.0, "source_file": "Phase 1/POC/Geminipro2.5/test-doneproject-tailwind/MCSS-missing-vs-tailwind.md", "source_location": null, "weight": 1.0}, {"source": "tailwind_login_demo", "target": "mcss_embedded_login_demo", "relation": "semantically_similar_to", "confidence": "INFERRED", "confidence_score": 0.95, "source_file": "Phase 1/POC/Geminipro2.5/test-doneproject-tailwind/MCSS-missing-vs-tailwind.md", "source_location": null, "weight": 1.0}], "hyperedges": [{"id": "mcss_missing_features", "label": "MCSS gaps identified vs Tailwind and during POC", "nodes": ["mcss_vs_tailwind_comparison", "mcss_poc_customizations_doc", "mcss_poc_customizations_rec", "notification_bar_component", "login_container_custom", "tailwind_css"], "relation": "participate_in", "confidence": "EXTRACTED", "confidence_score": 1.0, "source_file": "Phase 1/POC/Geminipro2.5/test-doneproject-tailwind/MCSS-missing-vs-tailwind.md"}]}